{
  "result": "success",
  "provider": "https://www.exchangerate-api.com",
  "documentation": "https://www.exchangerate-api.com/docs/free",
  "terms_of_use": "https://www.exchangerate-api.com/terms",
  "time_last_update_unix": 1753833752,
  "time_last_update_utc": "Wed, 30 Jul 2025 00:02:32 +0000",
  "time_next_update_unix": 1753921742,
  "time_next_update_utc": "Thu, 31 Jul 2025 00:29:02 +0000",
  "time_eol_unix": 0,
  "base_code": "AOA",
  "rates": {
    "AOA": 1,
    "AED": 0.003991,
    "AFN": 0.074509,
    "ALL": 0.0912,
    "AMD": 0.415852,
    "ANG": 0.001945,
    "ARS": 1.409244,
    "AUD": 0.001634,
    "AWG": 0.001945,
    "AZN": 0.001843,
    "BAM": 0.001803,
    "BBD": 0.002174,
    "BDT": 0.131549,
    "BGN": 0.001803,
    "BHD": 0.000409,
    "BIF": 3.245074,
    "BMD": 0.001087,
    "BND": 0.001381,
    "BOB": 0.007506,
    "BRL": 0.005993,
    "BSD": 0.001087,
    "BTN": 0.093182,
    "BWP": 0.015238,
    "BYN": 0.003562,
    "BZD": 0.002174,
    "CAD": 0.001464,
    "CDF": 3.150962,
    "CHF": 0.000858,
    "CLP": 1.047468,
    "CNY": 0.007641,
    "COP": 4.532839,
    "CRC": 0.548041,
    "CUP": 0.026084,
    "CVE": 0.101621,
    "CZK": 0.022848,
    "DJF": 0.19315,
    "DKK": 0.006876,
    "DOP": 0.065857,
    "DZD": 0.140798,
    "EGP": 0.052236,
    "ERN": 0.016302,
    "ETB": 0.15031,
    "EUR": 0.000922,
    "FJD": 0.00242,
    "FKP": 0.000798,
    "FOK": 0.006876,
    "GBP": 0.000798,
    "GEL": 0.002931,
    "GGP": 0.000798,
    "GHS": 0.011953,
    "GIP": 0.000798,
    "GMD": 0.078039,
    "GNF": 9.326052,
    "GTQ": 0.008317,
    "GYD": 0.226725,
    "HKD": 0.008416,
    "HNL": 0.028507,
    "HRK": 0.006944,
    "HTG": 0.142132,
    "HUF": 0.370015,
    "IDR": 17.421053,
    "ILS": 0.003587,
    "IMP": 0.000798,
    "INR": 0.09319,
    "IQD": 1.420677,
    "IRR": 47.265198,
    "ISK": 0.131915,
    "JEP": 0.000798,
    "JMD": 0.173674,
    "JOD": 0.000771,
    "JPY": 0.158023,
    "KES": 0.139648,
    "KGS": 0.094661,
    "KHR": 4.355372,
    "KID": 0.001634,
    "KMF": 0.4534,
    "KRW": 1.491147,
    "KWD": 0.000331,
    "KYD": 0.000906,
    "KZT": 0.58791,
    "LAK": 23.640458,
    "LBP": 97.270169,
    "LKR": 0.323907,
    "LRD": 0.217342,
    "LSL": 0.019059,
    "LYD": 0.005871,
    "MAD": 0.00991,
    "MDL": 0.018147,
    "MGA": 4.866729,
    "MKD": 0.057565,
    "MMK": 2.282811,
    "MNT": 3.894274,
    "MOP": 0.008668,
    "MRU": 0.043054,
    "MUR": 0.049145,
    "MVR": 0.016757,
    "MWK": 1.869762,
    "MXN": 0.020155,
    "MYR": 0.004595,
    "MZN": 0.068846,
    "NAD": 0.019059,
    "NGN": 1.653213,
    "NIO": 0.039887,
    "NOK": 0.010878,
    "NPR": 0.149092,
    "NZD": 0.0018,
    "OMR": 0.000418,
    "PAB": 0.001087,
    "PEN": 0.003843,
    "PGK": 0.004561,
    "PHP": 0.062101,
    "PKR": 0.30682,
    "PLN": 0.003964,
    "PYG": 8.074259,
    "QAR": 0.003956,
    "RON": 0.004709,
    "RSD": 0.109625,
    "RUB": 0.087698,
    "RWF": 1.553775,
    "SAR": 0.004076,
    "SBD": 0.008841,
    "SCR": 0.015942,
    "SDG": 0.487058,
    "SEK": 0.010273,
    "SGD": 0.001381,
    "SHP": 0.000798,
    "SLE": 0.024899,
    "SLL": 24.89899,
    "SOS": 0.619882,
    "SRD": 0.039675,
    "SSP": 4.99808,
    "STN": 0.022579,
    "SYP": 13.796626,
    "SZL": 0.019059,
    "THB": 0.034819,
    "TJS": 0.010406,
    "TMT": 0.00381,
    "TND": 0.003093,
    "TOP": 0.002582,
    "TRY": 0.043514,
    "TTD": 0.007387,
    "TVD": 0.001634,
    "TWD": 0.031839,
    "TZS": 2.767782,
    "UAH": 0.045262,
    "UGX": 3.848076,
    "USD": 0.001087,
    "UYU": 0.043376,
    "UZS": 13.792342,
    "VES": 0.134632,
    "VND": 27.595836,
    "VUV": 0.130186,
    "WST": 0.002978,
    "XAF": 0.604533,
    "XCD": 0.002934,
    "XCG": 0.001945,
    "XDR": 0.000799,
    "XOF": 0.604533,
    "XPF": 0.109977,
    "YER": 0.260854,
    "ZAR": 0.019062,
    "ZMW": 0.0248,
    "ZWL": 0.029122
  }
}