{
  "result": "success",
  "provider": "https://www.exchangerate-api.com",
  "documentation": "https://www.exchangerate-api.com/docs/free",
  "terms_of_use": "https://www.exchangerate-api.com/terms",
  "time_last_update_unix": 1753833752,
  "time_last_update_utc": "Wed, 30 Jul 2025 00:02:32 +0000",
  "time_next_update_unix": 1753921742,
  "time_next_update_utc": "Thu, 31 Jul 2025 00:29:02 +0000",
  "time_eol_unix": 0,
  "base_code": "BHD",
  "rates": {
    "BHD": 1,
    "AED": 9.767287,
    "AFN": 183.287317,
    "ALL": 224.565937,
    "AMD": 1020.877374,
    "ANG": 4.760638,
    "AOA": 2447.121433,
    "ARS": 3448.590426,
    "AUD": 4.085798,
    "AWG": 4.760638,
    "AZN": 4.52966,
    "BAM": 4.502293,
    "BBD": 5.319149,
    "BDT": 326.652124,
    "BGN": 4.502293,
    "BIF": 7900.810607,
    "BMD": 2.659574,
    "BND": 3.426021,
    "BOB": 18.450759,
    "BRL": 14.869765,
    "BSD": 2.659574,
    "BTN": 231.316581,
    "BWP": 36.798766,
    "BYN": 8.373698,
    "BZD": 5.319149,
    "CAD": 3.661725,
    "CDF": 7679.08776,
    "CHF": 2.143452,
    "CLP": 2569.147207,
    "CNY": 19.097046,
    "COP": 11131.924191,
    "CRC": 1347.700202,
    "CUP": 63.829787,
    "CVE": 253.828489,
    "CZK": 56.655013,
    "DJF": 472.662234,
    "DKK": 17.17369,
    "DOP": 161.710893,
    "DZD": 347.195903,
    "EGP": 129.452826,
    "ERN": 39.893617,
    "ETB": 365.339138,
    "EUR": 2.301998,
    "FJD": 5.981659,
    "FKP": 1.992727,
    "FOK": 17.177668,
    "GBP": 1.992729,
    "GEL": 7.19576,
    "GGP": 1.992727,
    "GHS": 29.66643,
    "GIP": 1.992727,
    "GMD": 193.59403,
    "GNF": 23134.866326,
    "GTQ": 20.460081,
    "GYD": 556.327194,
    "HKD": 20.87826,
    "HNL": 70.057513,
    "HRK": 17.344314,
    "HTG": 348.493621,
    "HUF": 920.366142,
    "IDR": 43602.608499,
    "ILS": 8.959339,
    "IMP": 1.992727,
    "INR": 231.317345,
    "IQD": 3485.984101,
    "IRR": 112895.486512,
    "ISK": 327.56059,
    "JEP": 1.992727,
    "JMD": 425.695544,
    "JOD": 1.885638,
    "JPY": 395.022497,
    "KES": 343.489692,
    "KGS": 231.296002,
    "KHR": 10686.987578,
    "KID": 4.085795,
    "KMF": 1132.502884,
    "KRW": 3696.701543,
    "KWD": 0.813235,
    "KYD": 2.216311,
    "KZT": 1444.150867,
    "LAK": 57669.291619,
    "LBP": 238031.914894,
    "LKR": 802.932717,
    "LRD": 534.677905,
    "LSL": 47.586167,
    "LYD": 14.40611,
    "MAD": 24.18394,
    "MDL": 44.909457,
    "MGA": 11827.98425,
    "MKD": 140.708653,
    "MMK": 5605.238639,
    "MNT": 9485.174796,
    "MOP": 21.504608,
    "MRU": 105.643938,
    "MUR": 122.399871,
    "MVR": 41.10294,
    "MWK": 4638.578144,
    "MXN": 49.918153,
    "MYR": 11.260159,
    "MZN": 169.323666,
    "NAD": 47.586167,
    "NGN": 4070.509876,
    "NIO": 98.043096,
    "NOK": 27.143074,
    "NPR": 370.10653,
    "NZD": 4.467351,
    "OMR": 1.022598,
    "PAB": 2.659574,
    "PEN": 9.488572,
    "PGK": 11.126857,
    "PHP": 152.542259,
    "PKR": 753.452586,
    "PLN": 9.84812,
    "PYG": 20126.049449,
    "QAR": 9.680851,
    "RON": 11.683776,
    "RSD": 269.889847,
    "RUB": 216.769983,
    "RWF": 3854.483415,
    "SAR": 9.973404,
    "SBD": 21.919784,
    "SCR": 39.192746,
    "SDG": 1195.13365,
    "SEK": 25.672657,
    "SGD": 3.426022,
    "SHP": 1.992727,
    "SLE": 60.873967,
    "SLL": 60873.966843,
    "SOS": 1521.035381,
    "SRD": 97.351443,
    "SSP": 12501.040434,
    "STN": 56.398658,
    "SYP": 34408.797119,
    "SZL": 47.586167,
    "THB": 86.251879,
    "TJS": 25.687339,
    "TMT": 9.308547,
    "TND": 7.695746,
    "TOP": 6.349172,
    "TRY": 107.961978,
    "TTD": 18.028265,
    "TVD": 4.085795,
    "TWD": 78.948705,
    "TZS": 6806.902513,
    "UAH": 111.330239,
    "UGX": 9545.147208,
    "USD": 2.659574,
    "UYU": 106.702301,
    "UZS": 33409.317213,
    "VES": 329.446277,
    "VND": 69536.773079,
    "VUV": 317.006517,
    "WST": 7.27958,
    "XAF": 1510.003846,
    "XCD": 7.180851,
    "XCG": 4.760638,
    "XDR": 1.955482,
    "XOF": 1510.003846,
    "XPF": 274.700596,
    "YER": 642.265475,
    "ZAR": 47.586227,
    "ZMW": 61.521581,
    "ZWL": 71.2625
  }
}