{
  "result": "success",
  "provider": "https://www.exchangerate-api.com",
  "documentation": "https://www.exchangerate-api.com/docs/free",
  "terms_of_use": "https://www.exchangerate-api.com/terms",
  "time_last_update_unix": 1753833752,
  "time_last_update_utc": "Wed, 30 Jul 2025 00:02:32 +0000",
  "time_next_update_unix": 1753921742,
  "time_next_update_utc": "Thu, 31 Jul 2025 00:29:02 +0000",
  "time_eol_unix": 0,
  "base_code": "MKD",
  "rates": {
    "MKD": 1,
    "AED": 0.069415,
    "AFN": 1.306298,
    "ALL": 1.572324,
    "AMD": 7.251693,
    "ANG": 0.033833,
    "AOA": 17.371704,
    "ARS": 24.50873,
    "AUD": 0.028955,
    "AWG": 0.033833,
    "AZN": 0.032147,
    "BAM": 0.031721,
    "BBD": 0.037803,
    "BDT": 2.305084,
    "BGN": 0.031721,
    "BHD": 0.007107,
    "BIF": 56.34375,
    "BMD": 0.018901,
    "BND": 0.024348,
    "BOB": 0.130952,
    "BRL": 0.105678,
    "BSD": 0.018901,
    "BTN": 1.643939,
    "BWP": 0.252354,
    "BYN": 0.06188,
    "BZD": 0.037803,
    "CAD": 0.025937,
    "CDF": 55.031325,
    "CHF": 0.015139,
    "CLP": 18.25863,
    "CNY": 0.13572,
    "COP": 77.068616,
    "CRC": 9.552984,
    "CUP": 0.453631,
    "CVE": 1.788361,
    "CZK": 0.402641,
    "DJF": 3.359155,
    "DKK": 0.120998,
    "DOP": 1.143806,
    "DZD": 2.4535,
    "EGP": 0.929634,
    "ERN": 0.283519,
    "ETB": 2.635154,
    "EUR": 0.016219,
    "FJD": 0.042371,
    "FKP": 0.014076,
    "FOK": 0.120998,
    "GBP": 0.014076,
    "GEL": 0.051206,
    "GGP": 0.014076,
    "GHS": 0.198075,
    "GIP": 0.014076,
    "GMD": 1.375783,
    "GNF": 163.909091,
    "GTQ": 0.145126,
    "GYD": 3.954176,
    "HKD": 0.148379,
    "HNL": 0.495043,
    "HRK": 0.1222,
    "HTG": 2.482391,
    "HUF": 6.540935,
    "IDR": 309.878657,
    "ILS": 0.063673,
    "IMP": 0.014076,
    "INR": 1.643945,
    "IQD": 24.770065,
    "IRR": 796.674419,
    "ISK": 2.327935,
    "JEP": 0.014076,
    "JMD": 3.031593,
    "JOD": 0.013401,
    "JPY": 2.800336,
    "KES": 2.443089,
    "KGS": 1.654928,
    "KHR": 75.789823,
    "KID": 0.028955,
    "KMF": 7.979106,
    "KRW": 26.272027,
    "KWD": 0.00577,
    "KYD": 0.015751,
    "KZT": 10.198571,
    "LAK": 407.821429,
    "LBP": 1691.665079,
    "LKR": 5.705696,
    "LRD": 3.785304,
    "LSL": 0.338192,
    "LYD": 0.102459,
    "MAD": 0.170179,
    "MDL": 0.319711,
    "MGA": 83.451888,
    "MMK": 39.718261,
    "MNT": 67.835644,
    "MOP": 0.152831,
    "MRU": 0.754559,
    "MUR": 0.857497,
    "MVR": 0.292295,
    "MWK": 32.781818,
    "MXN": 0.354762,
    "MYR": 0.080025,
    "MZN": 1.20836,
    "NAD": 0.338192,
    "NGN": 28.896668,
    "NIO": 0.695574,
    "NOK": 0.192396,
    "NPR": 2.630303,
    "NZD": 0.031749,
    "OMR": 0.007267,
    "PAB": 0.018901,
    "PEN": 0.067402,
    "PGK": 0.079492,
    "PHP": 1.0841,
    "PKR": 5.394803,
    "PLN": 0.068514,
    "PYG": 141.557851,
    "QAR": 0.068801,
    "RON": 0.083035,
    "RSD": 1.887438,
    "RUB": 1.486204,
    "RWF": 27.329079,
    "SAR": 0.07088,
    "SBD": 0.154694,
    "SCR": 0.273509,
    "SDG": 11.352775,
    "SEK": 0.180914,
    "SGD": 0.024348,
    "SHP": 0.014076,
    "SLE": 0.432538,
    "SLL": 432.537879,
    "SOS": 10.806625,
    "SRD": 0.695574,
    "SSP": 85.6425,
    "STN": 0.39736,
    "SYP": 245.569892,
    "SZL": 0.338192,
    "THB": 0.612982,
    "TJS": 0.180776,
    "TMT": 0.066191,
    "TND": 0.054363,
    "TOP": 0.044851,
    "TRY": 0.766225,
    "TTD": 0.128327,
    "TVD": 0.028955,
    "TWD": 0.554769,
    "TZS": 49.149211,
    "UAH": 0.791211,
    "UGX": 67.902874,
    "USD": 0.018901,
    "UYU": 0.760422,
    "UZS": 240.4,
    "VES": 2.341336,
    "VND": 494.257683,
    "VUV": 2.261561,
    "WST": 0.051857,
    "XAF": 10.638808,
    "XCD": 0.051033,
    "XCG": 0.033833,
    "XDR": 0.013897,
    "XOF": 10.638808,
    "XPF": 1.935417,
    "YER": 4.553333,
    "ZAR": 0.33819,
    "ZMW": 0.438349,
    "ZWL": 0.506454
  }
}