{
  "result": "success",
  "provider": "https://www.exchangerate-api.com",
  "documentation": "https://www.exchangerate-api.com/docs/free",
  "terms_of_use": "https://www.exchangerate-api.com/terms",
  "time_last_update_unix": 1753833752,
  "time_last_update_utc": "Wed, 30 Jul 2025 00:02:32 +0000",
  "time_next_update_unix": 1753921742,
  "time_next_update_utc": "Thu, 31 Jul 2025 00:29:02 +0000",
  "time_eol_unix": 0,
  "base_code": "ZWL",
  "rates": {
    "ZWL": 1,
    "AED": 0.137061,
    "AFN": 2.572002,
    "ALL": 3.15125,
    "AMD": 14.32559,
    "ANG": 0.066804,
    "AOA": 34.339539,
    "ARS": 48.392779,
    "AUD": 0.057334,
    "AWG": 0.066804,
    "AZN": 0.063563,
    "BAM": 0.062998,
    "BBD": 0.074642,
    "BDT": 4.583787,
    "BGN": 0.062998,
    "BHD": 0.014033,
    "BIF": 110.869119,
    "BMD": 0.037321,
    "BND": 0.048075,
    "BOB": 0.258913,
    "BRL": 0.208662,
    "BSD": 0.037321,
    "BTN": 3.245978,
    "BWP": 0.520427,
    "BYN": 0.117505,
    "BZD": 0.074642,
    "CAD": 0.051384,
    "CDF": 107.757765,
    "CHF": 0.030078,
    "CLP": 36.051881,
    "CNY": 0.267982,
    "COP": 156.210127,
    "CRC": 18.911773,
    "CUP": 0.8957,
    "CVE": 3.5517,
    "CZK": 0.795019,
    "DJF": 6.632692,
    "DKK": 0.240303,
    "DOP": 2.269228,
    "DZD": 4.87207,
    "EGP": 1.816563,
    "ERN": 0.559812,
    "ETB": 5.126667,
    "EUR": 0.032211,
    "FJD": 0.083938,
    "FKP": 0.027956,
    "FOK": 0.240303,
    "GBP": 0.027956,
    "GEL": 0.100975,
    "GGP": 0.027956,
    "GHS": 0.416298,
    "GIP": 0.027956,
    "GMD": 2.716633,
    "GNF": 324.642923,
    "GTQ": 0.287109,
    "GYD": 7.806731,
    "HKD": 0.292977,
    "HNL": 0.983091,
    "HRK": 0.242691,
    "HTG": 4.890281,
    "HUF": 12.915154,
    "IDR": 611.859091,
    "ILS": 0.125723,
    "IMP": 0.027956,
    "INR": 3.24599,
    "IQD": 48.917511,
    "IRR": 1584.220121,
    "ISK": 4.596535,
    "JEP": 0.027956,
    "JMD": 5.973626,
    "JOD": 0.02646,
    "JPY": 5.543203,
    "KES": 4.820062,
    "KGS": 3.24569,
    "KHR": 149.966498,
    "KID": 0.057331,
    "KMF": 15.846567,
    "KRW": 51.87443,
    "KWD": 0.011412,
    "KYD": 0.031101,
    "KZT": 20.265229,
    "LAK": 809.251592,
    "LBP": 3340.212803,
    "LKR": 11.267254,
    "LRD": 7.502935,
    "LSL": 0.6685,
    "LYD": 0.202156,
    "MAD": 0.339364,
    "MDL": 0.630198,
    "MGA": 165.977677,
    "MKD": 1.974512,
    "MMK": 78.656217,
    "MNT": 133.101909,
    "MOP": 0.301766,
    "MRU": 1.482462,
    "MUR": 1.717592,
    "MVR": 0.576782,
    "MWK": 65.091432,
    "MXN": 0.700483,
    "MYR": 0.15801,
    "MZN": 2.376056,
    "NAD": 0.6685,
    "NGN": 57.119942,
    "NIO": 1.375802,
    "NOK": 0.380889,
    "NPR": 5.193565,
    "NZD": 0.062689,
    "OMR": 0.01435,
    "PAB": 0.037321,
    "PEN": 0.13315,
    "PGK": 0.156139,
    "PHP": 2.140568,
    "PKR": 10.572918,
    "PLN": 0.138195,
    "PYG": 282.421322,
    "QAR": 0.135848,
    "RON": 0.163954,
    "RSD": 3.787263,
    "RUB": 3.041852,
    "RWF": 54.088524,
    "SAR": 0.139953,
    "SBD": 0.307592,
    "SCR": 0.549977,
    "SDG": 16.770863,
    "SEK": 0.360255,
    "SGD": 0.048076,
    "SHP": 0.027956,
    "SLE": 0.854222,
    "SLL": 854.221601,
    "SOS": 21.34412,
    "SRD": 1.366096,
    "SSP": 175.422423,
    "STN": 0.789159,
    "SYP": 482.845776,
    "SZL": 0.6685,
    "THB": 1.21034,
    "TJS": 0.360461,
    "TMT": 0.130623,
    "TND": 0.107992,
    "TOP": 0.089096,
    "TRY": 1.51499,
    "TTD": 0.252984,
    "TVD": 0.057331,
    "TWD": 1.107858,
    "TZS": 95.518716,
    "UAH": 1.562256,
    "UGX": 133.943479,
    "USD": 0.037321,
    "UYU": 1.497313,
    "UZS": 468.820448,
    "VES": 4.622996,
    "VND": 975.783519,
    "VUV": 4.448434,
    "WST": 0.102152,
    "XAF": 21.128755,
    "XCD": 0.100766,
    "XCG": 0.066804,
    "XDR": 0.027441,
    "XOF": 21.128755,
    "XPF": 3.843753,
    "YER": 9.012671,
    "ZAR": 0.6685,
    "ZMW": 0.863309
  }
}