{
  "result": "success",
  "provider": "https://www.exchangerate-api.com",
  "documentation": "https://www.exchangerate-api.com/docs/free",
  "terms_of_use": "https://www.exchangerate-api.com/terms",
  "time_last_update_unix": 1753747351,
  "time_last_update_utc": "Tue, 29 Jul 2025 00:02:31 +0000",
  "time_next_update_unix": 1753835181,
  "time_next_update_utc": "Wed, 30 Jul 2025 00:26:21 +0000",
  "time_eol_unix": 0,
  "base_code": "AED",
  "rates": {
    "AED": 1,
    "AFN": 18.68039,
    "ALL": 22.718267,
    "AMD": 104.565902,
    "ANG": 0.487406,
    "AOA": 250.319024,
    "ARS": 350.532335,
    "AUD": 0.417395,
    "AWG": 0.487406,
    "AZN": 0.46317,
    "BAM": 0.458341,
    "BBD": 0.544588,
    "BDT": 33.338812,
    "BGN": 0.458341,
    "BHD": 0.102383,
    "BIF": 808.429091,
    "BMD": 0.272294,
    "BND": 0.350021,
    "BOB": 1.881703,
    "BRL": 1.519952,
    "BSD": 0.272294,
    "BTN": 23.615983,
    "BWP": 3.740698,
    "BYN": 0.85533,
    "BZD": 0.544588,
    "CAD": 0.373805,
    "CDF": 785.375461,
    "CHF": 0.218447,
    "CLP": 261.729769,
    "CNY": 1.953742,
    "COP": 1124.217349,
    "CRC": 137.560425,
    "CUP": 6.535058,
    "CVE": 25.840155,
    "CZK": 5.765776,
    "DJF": 48.392376,
    "DKK": 1.74831,
    "DOP": 16.51729,
    "DZD": 35.326199,
    "EGP": 13.287162,
    "ERN": 4.084411,
    "ETB": 37.447824,
    "EUR": 0.234348,
    "FJD": 0.61118,
    "FKP": 0.203453,
    "FOK": 1.749947,
    "GBP": 0.203454,
    "GEL": 0.736824,
    "GGP": 0.203453,
    "GHS": 3.031805,
    "GIP": 0.203453,
    "GMD": 19.817981,
    "GNF": 2367.200415,
    "GTQ": 2.089817,
    "GYD": 56.962039,
    "HKD": 2.137509,
    "HNL": 7.130025,
    "HRK": 1.765679,
    "HTG": 35.634673,
    "HUF": 93.123694,
    "IDR": 4457.519759,
    "ILS": 0.913095,
    "IMP": 0.203453,
    "INR": 23.616029,
    "IQD": 356.458313,
    "IRR": 11553.662981,
    "ISK": 33.255699,
    "JEP": 0.203453,
    "JMD": 43.541157,
    "JOD": 0.193057,
    "JPY": 40.399402,
    "KES": 35.191765,
    "KGS": 23.681306,
    "KHR": 1092.726718,
    "KID": 0.417395,
    "KMF": 115.290642,
    "KRW": 377.773738,
    "KWD": 0.083133,
    "KYD": 0.226912,
    "KZT": 147.848722,
    "LAK": 5877.276925,
    "LBP": 24370.319946,
    "LKR": 82.150904,
    "LRD": 54.600232,
    "LSL": 4.870065,
    "LYD": 1.470052,
    "MAD": 2.456786,
    "MDL": 4.575994,
    "MGA": 1204.635377,
    "MKD": 14.340879,
    "MMK": 572.299205,
    "MNT": 971.539502,
    "MOP": 2.201635,
    "MRU": 10.879984,
    "MUR": 12.342062,
    "MVR": 4.209253,
    "MWK": 474.613079,
    "MXN": 5.097502,
    "MYR": 1.151746,
    "MZN": 17.326107,
    "NAD": 4.870065,
    "NGN": 416.199655,
    "NIO": 10.019055,
    "NOK": 2.773571,
    "NPR": 37.785573,
    "NZD": 0.45583,
    "OMR": 0.104696,
    "PAB": 0.272294,
    "PEN": 0.964693,
    "PGK": 1.138798,
    "PHP": 15.574715,
    "PKR": 77.158369,
    "PLN": 0.998696,
    "PYG": 2079.785285,
    "QAR": 0.99115,
    "RON": 1.186843,
    "RSD": 27.323005,
    "RUB": 21.888452,
    "RWF": 394.39309,
    "SAR": 1.021103,
    "SBD": 2.26292,
    "SCR": 3.920308,
    "SDG": 123.69725,
    "SEK": 2.61303,
    "SGD": 0.350021,
    "SHP": 0.203453,
    "SLE": 6.232433,
    "SLL": 6232.433365,
    "SOS": 155.532455,
    "SRD": 10.063436,
    "SSP": 1278.764475,
    "STN": 5.741475,
    "SYP": 3514.717788,
    "SZL": 4.870065,
    "THB": 8.829723,
    "TJS": 2.809447,
    "TMT": 0.953046,
    "TND": 0.782902,
    "TOP": 0.649223,
    "TRY": 11.046458,
    "TTD": 1.843547,
    "TVD": 0.417395,
    "TWD": 8.063537,
    "TZS": 696.165765,
    "UAH": 11.382637,
    "UGX": 976.552665,
    "USD": 0.272294,
    "UYU": 10.894363,
    "UZS": 3425.606436,
    "VES": 33.448822,
    "VND": 7104.133,
    "VUV": 32.402476,
    "WST": 0.740888,
    "XAF": 153.720857,
    "XCD": 0.735194,
    "XCG": 0.487406,
    "XDR": 0.199257,
    "XOF": 153.720857,
    "XPF": 27.964969,
    "YER": 65.630383,
    "ZAR": 4.870075,
    "ZMW": 6.356704,
    "ZWL": 7.295167
  }
}