{
  "result": "success",
  "provider": "https://www.exchangerate-api.com",
  "documentation": "https://www.exchangerate-api.com/docs/free",
  "terms_of_use": "https://www.exchangerate-api.com/terms",
  "time_last_update_unix": 1754265752,
  "time_last_update_utc": "Mon, 04 Aug 2025 00:02:32 +0000",
  "time_next_update_unix": 1754353502,
  "time_next_update_utc": "Tue, 05 Aug 2025 00:25:02 +0000",
  "time_eol_unix": 0,
  "base_code": "DJF",
  "rates": {
    "DJF": 1,
    "AED": 0.020664,
    "AFN": 0.386982,
    "ALL": 0.477842,
    "AMD": 2.158083,
    "ANG": 0.010072,
    "AOA": 5.164576,
    "ARS": 7.659928,
    "AUD": 0.008705,
    "AWG": 0.010072,
    "AZN": 0.009562,
    "BAM": 0.009511,
    "BBD": 0.011254,
    "BDT": 0.686953,
    "BGN": 0.009511,
    "BHD": 0.002116,
    "BIF": 16.816271,
    "BMD": 0.005627,
    "BND": 0.007254,
    "BOB": 0.038885,
    "BRL": 0.031553,
    "BSD": 0.005627,
    "BTN": 0.491451,
    "BWP": 0.079478,
    "BYN": 0.018275,
    "BZD": 0.011254,
    "CAD": 0.007758,
    "CDF": 16.335641,
    "CHF": 0.004532,
    "CLP": 5.469641,
    "CNY": 0.040504,
    "COP": 23.42298,
    "CRC": 2.841209,
    "CUP": 0.135043,
    "CVE": 0.536221,
    "CZK": 0.120152,
    "DKK": 0.03628,
    "DOP": 0.34249,
    "DZD": 0.736602,
    "EGP": 0.27357,
    "ERN": 0.084402,
    "ETB": 0.777052,
    "EUR": 0.004868,
    "FJD": 0.012766,
    "FKP": 0.004243,
    "FOK": 0.036275,
    "GBP": 0.004243,
    "GEL": 0.015211,
    "GGP": 0.004243,
    "GHS": 0.059741,
    "GIP": 0.004243,
    "GMD": 0.409822,
    "GNF": 49.068357,
    "GTQ": 0.043162,
    "GYD": 1.177054,
    "HKD": 0.044169,
    "HNL": 0.147781,
    "HRK": 0.03664,
    "HTG": 0.737806,
    "HUF": 1.933432,
    "IDR": 92.498077,
    "ILS": 0.019217,
    "IMP": 0.004243,
    "INR": 0.491452,
    "IQD": 7.379887,
    "IRR": 242.802766,
    "ISK": 0.700607,
    "JEP": 0.004243,
    "JMD": 0.900088,
    "JOD": 0.003989,
    "JPY": 0.830124,
    "KES": 0.726729,
    "KGS": 0.491681,
    "KHR": 22.619309,
    "KID": 0.008705,
    "KMF": 2.392447,
    "KRW": 7.828437,
    "KWD": 0.001721,
    "KYD": 0.004689,
    "KZT": 3.055546,
    "LAK": 121.790899,
    "LBP": 503.598337,
    "LKR": 1.694663,
    "LRD": 1.128545,
    "LSL": 0.101491,
    "LYD": 0.030734,
    "MAD": 0.051162,
    "MDL": 0.095725,
    "MGA": 25.216035,
    "MKD": 0.30277,
    "MMK": 11.823535,
    "MNT": 20.095433,
    "MOP": 0.045494,
    "MRU": 0.225562,
    "MUR": 0.262407,
    "MVR": 0.086823,
    "MWK": 9.781682,
    "MXN": 0.106235,
    "MYR": 0.024069,
    "MZN": 0.357898,
    "NAD": 0.101491,
    "NGN": 8.606952,
    "NIO": 0.206998,
    "NOK": 0.05771,
    "NPR": 0.786322,
    "NZD": 0.009518,
    "OMR": 0.002163,
    "PAB": 0.005627,
    "PEN": 0.020176,
    "PGK": 0.023553,
    "PHP": 0.325326,
    "PKR": 1.596642,
    "PLN": 0.020749,
    "PYG": 42.660708,
    "QAR": 0.020482,
    "RON": 0.024666,
    "RSD": 0.57041,
    "RUB": 0.450397,
    "RWF": 8.123401,
    "SAR": 0.0211,
    "SBD": 0.046464,
    "SCR": 0.082955,
    "SDG": 2.579017,
    "SEK": 0.054396,
    "SGD": 0.007254,
    "SHP": 0.004243,
    "SLE": 0.129207,
    "SLL": 129.206771,
    "SOS": 3.214417,
    "SRD": 0.207565,
    "SSP": 26.163717,
    "STN": 0.119144,
    "SYP": 72.604538,
    "SZL": 0.101491,
    "THB": 0.183336,
    "TJS": 0.054097,
    "TMT": 0.019697,
    "TND": 0.016347,
    "TOP": 0.013445,
    "TRY": 0.22893,
    "TTD": 0.038143,
    "TVD": 0.008705,
    "TWD": 0.167134,
    "TZS": 14.306951,
    "UAH": 0.235111,
    "UGX": 20.18589,
    "USD": 0.005627,
    "UYU": 0.226011,
    "UZS": 71.544396,
    "VES": 0.710553,
    "VND": 146.944902,
    "VUV": 0.670984,
    "WST": 0.015477,
    "XAF": 3.18993,
    "XCD": 0.015192,
    "XCG": 0.010072,
    "XDR": 0.004163,
    "XOF": 3.18993,
    "XPF": 0.580314,
    "YER": 1.352969,
    "ZAR": 0.101491,
    "ZMW": 0.129005,
    "ZWL": 0.150745
  }
}