{
  "result": "success",
  "provider": "https://www.exchangerate-api.com",
  "documentation": "https://www.exchangerate-api.com/docs/free",
  "terms_of_use": "https://www.exchangerate-api.com/terms",
  "time_last_update_unix": 1754265752,
  "time_last_update_utc": "Mon, 04 Aug 2025 00:02:32 +0000",
  "time_next_update_unix": 1754353422,
  "time_next_update_utc": "Tue, 05 Aug 2025 00:23:42 +0000",
  "time_eol_unix": 0,
  "base_code": "NPR",
  "rates": {
    "NPR": 1,
    "AED": 0.02628,
    "AFN": 0.491797,
    "ALL": 0.607343,
    "AMD": 2.74609,
    "ANG": 0.012809,
    "AOA": 6.601168,
    "ARS": 9.741467,
    "AUD": 0.011083,
    "AWG": 0.012809,
    "AZN": 0.01215,
    "BAM": 0.012096,
    "BBD": 0.014312,
    "BDT": 0.873891,
    "BGN": 0.012096,
    "BHD": 0.002691,
    "BIF": 21.464461,
    "BMD": 0.007156,
    "BND": 0.009225,
    "BOB": 0.049412,
    "BRL": 0.040076,
    "BSD": 0.007156,
    "BTN": 0.625,
    "BWP": 0.099402,
    "BYN": 0.023192,
    "BZD": 0.014312,
    "CAD": 0.009885,
    "CDF": 20.85119,
    "CHF": 0.005781,
    "CLP": 6.950814,
    "CNY": 0.051504,
    "COP": 29.773436,
    "CRC": 3.610663,
    "CUP": 0.17174,
    "CVE": 0.681935,
    "CZK": 0.152639,
    "DJF": 1.271744,
    "DKK": 0.046139,
    "DOP": 0.435244,
    "DZD": 0.93618,
    "EGP": 0.347905,
    "ERN": 0.107338,
    "ETB": 0.992914,
    "EUR": 0.006207,
    "FJD": 0.016186,
    "FKP": 0.005396,
    "FOK": 0.046133,
    "GBP": 0.005405,
    "GEL": 0.019353,
    "GGP": 0.005396,
    "GHS": 0.076106,
    "GIP": 0.005396,
    "GMD": 0.521708,
    "GNF": 62.481874,
    "GTQ": 0.054853,
    "GYD": 1.498546,
    "HKD": 0.056173,
    "HNL": 0.187801,
    "HRK": 0.046597,
    "HTG": 0.940049,
    "HUF": 2.492956,
    "IDR": 117.637847,
    "ILS": 0.02443,
    "IMP": 0.005396,
    "INR": 0.625,
    "IQD": 9.396459,
    "IRR": 310.784234,
    "ISK": 0.887901,
    "JEP": 0.005396,
    "JMD": 1.143817,
    "JOD": 0.005073,
    "JPY": 1.068084,
    "KES": 0.923656,
    "KGS": 0.625954,
    "KHR": 28.807566,
    "KID": 0.011071,
    "KMF": 3.042581,
    "KRW": 9.961293,
    "KWD": 0.002186,
    "KYD": 0.005963,
    "KZT": 3.882287,
    "LAK": 154.784126,
    "LBP": 640.448144,
    "LKR": 2.153722,
    "LRD": 1.434133,
    "LSL": 0.12907,
    "LYD": 0.039141,
    "MAD": 0.065226,
    "MDL": 0.121632,
    "MGA": 32.196691,
    "MKD": 0.385046,
    "MMK": 15.026349,
    "MNT": 25.577769,
    "MOP": 0.057857,
    "MRU": 0.287206,
    "MUR": 0.336042,
    "MVR": 0.110406,
    "MWK": 12.454036,
    "MXN": 0.135262,
    "MYR": 0.030643,
    "MZN": 0.456096,
    "NAD": 0.12907,
    "NGN": 10.938071,
    "NIO": 0.263063,
    "NOK": 0.073588,
    "NZD": 0.012109,
    "OMR": 0.002751,
    "PAB": 0.007156,
    "PEN": 0.025652,
    "PGK": 0.029943,
    "PHP": 0.413892,
    "PKR": 2.03132,
    "PLN": 0.026747,
    "PYG": 54.234631,
    "QAR": 0.026047,
    "RON": 0.031757,
    "RSD": 0.729802,
    "RUB": 0.572977,
    "RWF": 10.338258,
    "SAR": 0.026834,
    "SBD": 0.059167,
    "SCR": 0.105444,
    "SDG": 3.200841,
    "SEK": 0.069379,
    "SGD": 0.00925,
    "SHP": 0.005396,
    "SLE": 0.164318,
    "SLL": 164.317931,
    "SOS": 4.09229,
    "SRD": 0.26429,
    "SSP": 33.659909,
    "STN": 0.151521,
    "SYP": 92.244293,
    "SZL": 0.12907,
    "THB": 0.233748,
    "TJS": 0.068692,
    "TMT": 0.024987,
    "TND": 0.020774,
    "TOP": 0.017122,
    "TRY": 0.291092,
    "TTD": 0.048432,
    "TVD": 0.011071,
    "TWD": 0.212734,
    "TZS": 18.251509,
    "UAH": 0.298753,
    "UGX": 25.738433,
    "USD": 0.007156,
    "UYU": 0.287258,
    "UZS": 91.150846,
    "VES": 0.903642,
    "VND": 186.42283,
    "VUV": 0.854464,
    "WST": 0.019707,
    "XAF": 4.056774,
    "XCD": 0.019321,
    "XCG": 0.012809,
    "XDR": 0.005293,
    "XOF": 4.056774,
    "XPF": 0.73801,
    "YER": 1.719413,
    "ZAR": 0.129386,
    "ZMW": 0.164219,
    "ZWL": 0.191709
  }
}