{
  "result": "success",
  "provider": "https://www.exchangerate-api.com",
  "documentation": "https://www.exchangerate-api.com/docs/free",
  "terms_of_use": "https://www.exchangerate-api.com/terms",
  "time_last_update_unix": 1754265752,
  "time_last_update_utc": "Mon, 04 Aug 2025 00:02:32 +0000",
  "time_next_update_unix": 1754353422,
  "time_next_update_utc": "Tue, 05 Aug 2025 00:23:42 +0000",
  "time_eol_unix": 0,
  "base_code": "PEN",
  "rates": {
    "PEN": 1,
    "AED": 1.024201,
    "AFN": 19.178749,
    "ALL": 23.681565,
    "AMD": 107.102101,
    "ANG": 0.499202,
    "AOA": 256.35396,
    "ARS": 379.653055,
    "AUD": 0.432674,
    "AWG": 0.499202,
    "AZN": 0.473843,
    "BAM": 0.475127,
    "BBD": 0.557768,
    "BDT": 34.07832,
    "BGN": 0.475127,
    "BHD": 0.10486,
    "BIF": 836.521433,
    "BMD": 0.278884,
    "BND": 0.360958,
    "BOB": 1.927129,
    "BRL": 1.558223,
    "BSD": 0.278884,
    "BTN": 24.364518,
    "BWP": 3.871575,
    "BYN": 0.912068,
    "BZD": 0.557768,
    "CAD": 0.38581,
    "CDF": 812.93366,
    "CHF": 0.226238,
    "CLP": 270.938264,
    "CNY": 2.010516,
    "COP": 1160.829407,
    "CRC": 140.809733,
    "CUP": 6.693214,
    "CVE": 26.786527,
    "CZK": 5.97487,
    "DJF": 49.56353,
    "DKK": 1.81234,
    "DOP": 16.973717,
    "DZD": 36.505842,
    "EGP": 13.555023,
    "ERN": 4.183259,
    "ETB": 38.71014,
    "EUR": 0.242939,
    "FJD": 0.632686,
    "FKP": 0.211085,
    "FOK": 1.812339,
    "GBP": 0.211087,
    "GEL": 0.754891,
    "GGP": 0.211085,
    "GHS": 2.932768,
    "GIP": 0.211085,
    "GMD": 20.342461,
    "GNF": 2437.790663,
    "GTQ": 2.139113,
    "GYD": 58.425904,
    "HKD": 2.188548,
    "HNL": 7.323992,
    "HRK": 1.830346,
    "HTG": 36.649292,
    "HUF": 97.111053,
    "IDR": 4643.11151,
    "ILS": 0.95411,
    "IMP": 0.211085,
    "INR": 24.364524,
    "IQD": 366.318069,
    "IRR": 12159.768921,
    "ISK": 34.438434,
    "JEP": 0.211085,
    "JMD": 44.606602,
    "JOD": 0.197729,
    "JPY": 41.608819,
    "KES": 36.014024,
    "KGS": 24.425272,
    "KHR": 1122.760795,
    "KID": 0.43267,
    "KMF": 119.513059,
    "KRW": 389.77211,
    "KWD": 0.085277,
    "KYD": 0.232403,
    "KZT": 151.489844,
    "LAK": 6035.960979,
    "LBP": 24960.111408,
    "LKR": 84.052461,
    "LRD": 55.930444,
    "LSL": 5.076756,
    "LYD": 1.525543,
    "MAD": 2.545291,
    "MDL": 4.740495,
    "MGA": 1254.252342,
    "MKD": 14.888902,
    "MMK": 585.972745,
    "MNT": 1004.131406,
    "MOP": 2.254202,
    "MRU": 11.196284,
    "MUR": 13.040249,
    "MVR": 4.305665,
    "MWK": 484.944774,
    "MXN": 5.274563,
    "MYR": 1.192468,
    "MZN": 17.777369,
    "NAD": 5.076756,
    "NGN": 426.536463,
    "NIO": 10.258762,
    "NOK": 2.874371,
    "NPR": 38.983229,
    "NZD": 0.473912,
    "OMR": 0.10723,
    "PAB": 0.278884,
    "PGK": 1.16728,
    "PHP": 16.166433,
    "PKR": 79.065249,
    "PLN": 1.039081,
    "PYG": 2114.225103,
    "QAR": 1.015137,
    "RON": 1.233509,
    "RSD": 28.476433,
    "RUB": 22.357256,
    "RWF": 402.72997,
    "SAR": 1.045815,
    "SBD": 2.345005,
    "SCR": 4.112229,
    "SDG": 128.036117,
    "SEK": 2.717714,
    "SGD": 0.360961,
    "SHP": 0.211085,
    "SLE": 6.459677,
    "SLL": 6459.677419,
    "SOS": 159.555275,
    "SRD": 10.303,
    "SSP": 1274.541004,
    "STN": 5.951752,
    "SYP": 3598.241612,
    "SZL": 5.076756,
    "THB": 9.121261,
    "TJS": 2.694876,
    "TMT": 0.985706,
    "TND": 0.809456,
    "TOP": 0.670503,
    "TRY": 11.335571,
    "TTD": 1.889757,
    "TVD": 0.43267,
    "TWD": 8.332922,
    "TZS": 711.711361,
    "UAH": 11.648321,
    "UGX": 1003.984368,
    "USD": 0.278885,
    "UYU": 11.201059,
    "UZS": 3551.599491,
    "VES": 35.217614,
    "VND": 7238.789859,
    "VUV": 33.459001,
    "WST": 0.772651,
    "XAF": 159.350745,
    "XCD": 0.752987,
    "XCG": 0.499202,
    "XDR": 0.20631,
    "XOF": 159.350745,
    "XPF": 28.989161,
    "YER": 67.052843,
    "ZAR": 5.076952,
    "ZMW": 6.403623,
    "ZWL": 7.471488
  }
}